src/__init__.py
src/ontosys.py
src/version.py
ontosys-0.0.2.dist-info/entry_points.txt
ontosys-0.0.2.dist-info/METADATA
ontosys-0.0.2.dist-info/WHEEL
ontosys-0.0.2.dist-info/RECORD
